Dataconvertion/__init__.py
Dataconvertion/converter.py
MyImageProject-1.0.dist-info/License
MyImageProject-1.0.dist-info/METADATA
MyImageProject-1.0.dist-info/WHEEL
MyImageProject-1.0.dist-info/top_level.txt
MyImageProject-1.0.dist-info/RECORD
